pytest_bdd_report/__init__.py
pytest_bdd_report/attach.py
pytest_bdd_report/pytest_bdd_report.py
pytest_bdd_report/setup.py
pytest_bdd_report/entities/__init__.py
pytest_bdd_report/entities/feature.py
pytest_bdd_report/entities/scenario.py
pytest_bdd_report/entities/status_enum.py
pytest_bdd_report/entities/step.py
pytest_bdd_report/extensions/__init__.py
pytest_bdd_report/extensions/encoder.py
pytest_bdd_report/extensions/screenshot.py
pytest_bdd_report/extractor/__init__.py
pytest_bdd_report/extractor/base_extractor.py
pytest_bdd_report/extractor/extractor.py
pytest_bdd_report/loader/__init__.py
pytest_bdd_report/loader/json_loader.py
pytest_bdd_report/renderer/__init__.py
pytest_bdd_report/renderer/renderer.py
pytest_bdd_report/renderer/renderer_protocol.py
pytest_bdd_report/report/__init__.py
pytest_bdd_report/report/report.py
pytest_bdd_report/report/report_composer.py
pytest_bdd_report/report/report_file.py
pytest_bdd_report/summary/__init__.py
pytest_bdd_report/summary/summary.py
pytest_bdd_report/summary/summary_generator.py
pytest_bdd_report/templates/__init__.py
pytest_bdd_report/templates/feature_statistics_template.py
pytest_bdd_report/templates/feature_template.py
pytest_bdd_report/templates/report_template.py
pytest_bdd_report/templates/scenario_template.py
pytest_bdd_report/templates/step_template.py
pytest_bdd_report/templates/summary_template.py
pytest_bdd_report/templates/template.py
pytest_bdd_report/templates/html_templates/feature.html
pytest_bdd_report/templates/html_templates/feature_statistics.html
pytest_bdd_report/templates/html_templates/report.html
pytest_bdd_report/templates/html_templates/scenario.html
pytest_bdd_report/templates/html_templates/statistics.html
pytest_bdd_report/templates/html_templates/step.html
pytest_bdd_report/templates/html_templates/style.html
pytest_bdd_report/templates/html_templates/summary.html
pytest_bdd_report/templates/html_templates/components/badge.html
pytest_bdd_report-1.2.2.dist-info/licenses/LICENSE
pytest_bdd_report-1.2.2.dist-info/METADATA
pytest_bdd_report-1.2.2.dist-info/WHEEL
pytest_bdd_report-1.2.2.dist-info/entry_points.txt
pytest_bdd_report-1.2.2.dist-info/top_level.txt
pytest_bdd_report-1.2.2.dist-info/RECORD
