Metadata-Version: 2.4
Name: pytest_bdd_report
Version: 1.2.2
Summary: A pytest-bdd plugin for generating useful and informative BDD test reports
Author-email: Mattia Monti <mattiamonti2001@gmail.com>
Project-URL: Homepage, https://github.com/mattiamonti/pytest-bdd-report
Project-URL: Bug Tracker, https://github.com/mattiamonti/pytest-bdd-report/issues
Classifier: Programming Language :: Python :: 3
Classifier: License :: OSI Approved :: MIT License
Classifier: Operating System :: OS Independent
Requires-Python: >=3.5
License-File: LICENSE
Requires-Dist: pytest>=7.1.3
Requires-Dist: pytest-bdd<9.0.0,>=5.0.0
Requires-Dist: Jinja2>=3.1.2
Dynamic: license-file
